django_uniapi/__init__.py
django_uniapi/admin.py
django_uniapi/models.py
django_uniapi/tests.py
django_uniapi/urls.py
django_uniapi/views.py
django_uniapi-1.0.11.dist-info/METADATA
django_uniapi-1.0.11.dist-info/WHEEL
django_uniapi-1.0.11.dist-info/top_level.txt
django_uniapi-1.0.11.dist-info/RECORD
