Metadata-Version: 2.1
Name: django-uniapi
Version: 1.0.11
Summary: Django General/Universal API
Home-page: https://github.com/django-xxx/django-uniapi
Author: Hackathon
Author-email: kimi.huang@brightcells.com
Keywords: django-uniapi
Classifier: Development Status :: 5 - Production/Stable
Classifier: Environment :: Web Environment
Classifier: Framework :: Django
Classifier: Intended Audience :: Developers
Classifier: Programming Language :: Python
Classifier: Topic :: Software Development :: Libraries :: Python Modules
Classifier: Topic :: Office/Business :: Financial :: Spreadsheet
Requires-Dist: TimeConvert
Requires-Dist: django-response
Requires-Dist: django-six
